fastapi_gcs/__init__.py
fastapi_gcs/fgcs_check.py
fastapi_gcs/fgcs_delete.py
fastapi_gcs/fgcs_generate.py
fastapi_gcs/fgcs_streaming.py
fastapi_gcs/fgcs_upload.py
fastapi_gcs/fgcs_upload_validation.py
fast_api_gcs-0.0.11.dist-info/LICENSE
fast_api_gcs-0.0.11.dist-info/METADATA
fast_api_gcs-0.0.11.dist-info/WHEEL
fast_api_gcs-0.0.11.dist-info/top_level.txt
fast_api_gcs-0.0.11.dist-info/RECORD
