Metadata-Version: 2.1
Name: fast-api-gcs
Version: 0.0.11
Summary: Fast API Google Cloud Storage
Author-email: Bayu Satria Gemilang <bayu.code.lab@gmail.com>
Project-URL: Homepage, https://github.com/bayu-code-lab/fastapi-gcs
Project-URL: Bug Tracker, https://github.com/bayu-code-lab/fastapi-gcs/issues
Classifier: Programming Language :: Python :: 3
Classifier: License :: OSI Approved :: MIT License
Classifier: Operating System :: OS Independent
Requires-Python: >=3.7
License-File: LICENSE
Requires-Dist: google-cloud-storage (>=2.5.0)
Requires-Dist: fastapi (>=0.85.1)
